devrig/__init__.py
devrig-0.0.0a0.dist-info/licenses/LICENSE
devrig-0.0.0a0.dist-info/METADATA
devrig-0.0.0a0.dist-info/WHEEL
devrig-0.0.0a0.dist-info/entry_points.txt
devrig-0.0.0a0.dist-info/top_level.txt
devrig-0.0.0a0.dist-info/RECORD
