Metadata-Version: 2.4
Name: devrig
Version: 0.0.0a0
Summary: A standardized development rig that provides commands for linting, formatting, and testing Python projects.
Author-email: "mesotron.dev" <mail@mesotron.dev>
Maintainer-email: "mesotron.dev" <mail@mesotron.dev>
License:                                  Apache License
Project-URL: Homepage, https://github.com/nortosem/devrig
Project-URL: Repository, https://github.com/nortosem/devrig
Keywords: ruff,pytest,coverage,lint,dev,tools,quality
Classifier: Development Status :: 2 - Pre-Alpha
Classifier: Intended Audience :: Developers
Classifier: Operating System :: OS Independent
Classifier: License :: OSI Approved :: Apache Software License
Classifier: Programming Language :: Python :: 3
Classifier: Topic :: Software Development :: Libraries :: Python Modules
Requires-Python: >=3.13
License-File: LICENSE
Requires-Dist: click
Requires-Dist: coverage[toml]>=7.5.0
Requires-Dist: mypy~=1.16.1
Requires-Dist: mypy_extensions>=1.0.0
Requires-Dist: pytest>=8.0
Requires-Dist: pytest-mock>=3.14
Requires-Dist: ruff>=0.12
Provides-Extra: dev
Requires-Dist: pip-tools>=7.4.1; extra == "dev"
Requires-Dist: build>=1.2.1; extra == "dev"
Requires-Dist: twine>=5.1.1; extra == "dev"
Requires-Dist: keyring>=25.2.1; extra == "dev"
Requires-Dist: keyrings.google-artifactregistry-auth>=1.1.2; extra == "dev"
Requires-Dist: types-requests>=2.32.4.20250611; extra == "dev"
Dynamic: license-file
